scheduling_utils/__init__.py
scheduling_utils/schedulers.py
scheduling_utils/schedulers_cpp.py
scheduling_utils/test.py
scheduling_utils/test_speed.py
scheduling_utils/cpp_extensions/schedulers.so
scheduling_utils/cpp_extensions/schedulers_win.dll
scheduling_utils-0.2.3.dist-info/LICENSE
scheduling_utils-0.2.3.dist-info/METADATA
scheduling_utils-0.2.3.dist-info/WHEEL
scheduling_utils-0.2.3.dist-info/top_level.txt
scheduling_utils-0.2.3.dist-info/RECORD
