Metadata-Version: 2.1
Name: scheduling_utils
Version: 0.2.3
Summary: implementation of LR scheduling functions in c++, binded using ctypes
Home-page: https://github.com/SerezD/scheduling_utils
Author: DSerez
License: MIT
License-File: LICENSE
